codecam/__init__.py
codecam/cli.py
codecam/web.py
codecam/static/app.js
codecam/templates/index.html
codecam-0.2.7.dist-info/LICENSE
codecam-0.2.7.dist-info/METADATA
codecam-0.2.7.dist-info/WHEEL
codecam-0.2.7.dist-info/entry_points.txt
codecam-0.2.7.dist-info/top_level.txt
codecam-0.2.7.dist-info/RECORD
