Metadata-Version: 2.2
Name: codecam
Version: 0.2.7
Summary: Select and snapshot project files for sharing with LLMs
Author: Conor Mahany
License: Copyright (c) 2025 Conor Mahany
Project-URL: Homepage, https://github.com/laundrevity/codecam
Project-URL: Issues, https://github.com/laundrevity/codecam/issues
Classifier: Development Status :: 3 - Alpha
Classifier: Environment :: Console
Classifier: Programming Language :: Python :: 3
Classifier: Programming Language :: Python :: 3.8
Classifier: Programming Language :: Python :: 3.9
Classifier: Programming Language :: Python :: 3.10
Classifier: Programming Language :: Python :: 3.11
Classifier: Programming Language :: Python :: 3.12
Classifier: Framework :: Flask
Classifier: Intended Audience :: Developers
Classifier: Topic :: Utilities
Requires-Python: >=3.8
License-File: LICENSE
Requires-Dist: Flask>=3.0.0
Requires-Dist: platformdirs>=4.2.0
Requires-Dist: pathspec>=0.12.1
